MANIFEST.in
README.rst
setup.py
bin/skytap
skytap/.DS_Store
skytap/Environments.py
skytap/Environments.pyc
skytap/Exports.py
skytap/Exports.pyc
skytap/Groups.py
skytap/Groups.pyc
skytap/Labels.py
skytap/Labels.pyc
skytap/Projects.py
skytap/Projects.pyc
skytap/PublicIPs.py
skytap/PublicIPs.pyc
skytap/Quotas.py
skytap/Quotas.pyc
skytap/Templates.py
skytap/Templates.pyc
skytap/Users.py
skytap/Users.pyc
skytap/Vpns.py
skytap/Vpns.pyc
skytap/__init__.py
skytap/__init__.pyc
skytap.egg-info/PKG-INFO
skytap.egg-info/SOURCES.txt
skytap.egg-info/dependency_links.txt
skytap.egg-info/requires.txt
skytap.egg-info/top_level.txt
skytap/framework/ApiClient.py
skytap/framework/ApiClient.pyc
skytap/framework/Config.py
skytap/framework/Config.pyc
skytap/framework/Json.py
skytap/framework/Json.pyc
skytap/framework/Suspendable.py
skytap/framework/Suspendable.pyc
skytap/framework/Utils.py
skytap/framework/Utils.pyc
skytap/framework/__init__.py
skytap/framework/__init__.pyc
skytap/models/Environment.py
skytap/models/Environment.pyc
skytap/models/Export.py
skytap/models/Export.pyc
skytap/models/Group.py
skytap/models/Group.pyc
skytap/models/Interface.py
skytap/models/Interface.pyc
skytap/models/Interfaces.py
skytap/models/Interfaces.pyc
skytap/models/Label.py
skytap/models/Label.pyc
skytap/models/Note.py
skytap/models/Note.pyc
skytap/models/Notes.py
skytap/models/Notes.pyc
skytap/models/Project.py
skytap/models/Project.pyc
skytap/models/PublicIP.py
skytap/models/PublicIP.pyc
skytap/models/PublishedService.py
skytap/models/PublishedService.pyc
skytap/models/PublishedServices.py
skytap/models/PublishedServices.pyc
skytap/models/Quota.py
skytap/models/Quota.pyc
skytap/models/SkytapGroup.py
skytap/models/SkytapGroup.pyc
skytap/models/SkytapResource.py
skytap/models/SkytapResource.pyc
skytap/models/Template.py
skytap/models/Template.pyc
skytap/models/User.py
skytap/models/User.pyc
skytap/models/UserData.py
skytap/models/UserData.pyc
skytap/models/Vm.py
skytap/models/Vm.pyc
skytap/models/Vms.py
skytap/models/Vms.pyc
skytap/models/Vpn.py
skytap/models/Vpn.pyc
skytap/models/__init__.py
skytap/models/__init__.pyc