Metadata-Version: 1.1
Name: skytap
Version: 1.4.0
Summary: Skytap REST API access modules
Home-page: https://github.com/mapledyne/skytap
Author: Michael Knowles
Author-email: michael@mapledyne.com
License: MIT
Download-URL: https://github.com/mapledyne/skytap/tarball/v1.4.0
Keywords: skytap,cloud,client,rest,api,development
Platform: UNKNOWN
Classifier: Development Status :: 5 - Production/Stable
Classifier: Environment :: Console
Classifier: Programming Language :: Python
Classifier: Programming Language :: Python :: 2.6
Classifier: Programming Language :: Python :: 2.7
Classifier: Programming Language :: Python :: 3.3
Classifier: Programming Language :: Python :: 3.4
Classifier: Programming Language :: Python :: 3.5
Classifier: Intended Audience :: Developers
Classifier: Intended Audience :: Information Technology
Classifier: Intended Audience :: System Administrators
Classifier: Natural Language :: English
Classifier: License :: OSI Approved :: MIT License
Classifier: Operating System :: OS Independent
Classifier: Topic :: Software Development :: Libraries :: Python Modules
Classifier: Topic :: System :: Systems Administration
Classifier: Topic :: Internet
